hdsdk/__init__.py
hdsdk/algorithm_utils.py
hdsdk/exceptions.py
hdsdk/client/__init__.py
hdsdk/client/api.py
hdsdk/client/api_client.py
hdsdk/conf/__init__.py
hdsdk/conf/common_config.py
hdsdk/conf/port_config.py
hdsdk/conf/url_config.py
hdsdk/utils/__init__.py
hdsdk/utils/base_util.py
hdsdk/utils/data_util.py
hdsdk/utils/feature_utils/__init__.py
hdsdk/utils/feature_utils/constants.py
hdsdk/utils/feature_utils/corr.py
hdsdk/utils/feature_utils/dtw_dist.py
hdsdk/utils/feature_utils/mk_exam.py
hdsdk/utils/feature_utils/statistics.py
hdsdk/utils/time_utils/__init__.py
hdsdk/utils/time_utils/current_time.py
hdsdk/utils/time_utils/timestamp2utc.py
hdsdk/utils/time_utils/utc2timestamp.py
hdsdk-0.0.10.dist-info/METADATA
hdsdk-0.0.10.dist-info/WHEEL
hdsdk-0.0.10.dist-info/top_level.txt
hdsdk-0.0.10.dist-info/RECORD
