Metadata-Version: 2.1
Name: hdsdk
Version: 0.0.10
Summary: python sdk for hadian
Author: wanggf
Author-email: wanggf@hd.com
Classifier: Programming Language :: Python :: 3
Classifier: License :: OSI Approved :: MIT License
Classifier: Operating System :: OS Independent
Requires-Python: >=3
Requires-Dist: pandas
Requires-Dist: numpy
Requires-Dist: pymannkendall
